{
  "schema": "word-guess.v1",
  "dateISO": "2025-09-29",
  "level": "Easy",
  "timerMode": "stopwatch",
  "wordsPerPuzzle": 10,
  "entries": [
    {
      "id": 1,
      "answer": "bride",
      "scramble": "IRBED",
      "hint": {
        "index": 1,
        "letter": "r"
      }
    },
    {
      "id": 2,
      "answer": "crap",
      "scramble": "PRAC",
      "hint": {
        "index": 2,
        "letter": "a"
      }
    },
    {
      "id": 3,
      "answer": "yemen",
      "scramble": "EEYMN",
      "hint": {
        "index": 4,
        "letter": "n"
      }
    },
    {
      "id": 4,
      "answer": "itself",
      "scramble": "LITEFS",
      "hint": {
        "index": 3,
        "letter": "e"
      }
    },
    {
      "id": 5,
      "answer": "solved",
      "scramble": "EOSDLV",
      "hint": {
        "index": 1,
        "letter": "o"
      }
    },
    {
      "id": 6,
      "answer": "craig",
      "scramble": "GACIR",
      "hint": {
        "index": 3,
        "letter": "i"
      }
    },
    {
      "id": 7,
      "answer": "remote",
      "scramble": "OEMETR",
      "hint": {
        "index": 4,
        "letter": "t"
      }
    },
    {
      "id": 8,
      "answer": "saints",
      "scramble": "SATSNI",
      "hint": {
        "index": 0,
        "letter": "s"
      }
    },
    {
      "id": 9,
      "answer": "sports",
      "scramble": "OPSTRS",
      "hint": {
        "index": 1,
        "letter": "p"
      }
    },
    {
      "id": 10,
      "answer": "docs",
      "scramble": "DCOS",
      "hint": {
        "index": 3,
        "letter": "s"
      }
    }
  ],
  "meta": {
    "generatedBy": "build_word_guess_puzzles.py",
    "seed": 1337,
    "lengthBuckets": {
      "Easy": {
        "min": 4,
        "max": 6
      },
      "Medium": {
        "min": 7,
        "max": 9
      },
      "Hard": {
        "min": 10,
        "max": 12
      },
      "Godlike": {
        "min": 13,
        "max": 25
      }
    }
  }
}