{
  "schema": "word-guess.v1",
  "dateISO": "2025-04-06",
  "level": "Godlike",
  "timerMode": "stopwatch",
  "wordsPerPuzzle": 10,
  "entries": [
    {
      "id": 1,
      "answer": "documentation",
      "scramble": "DOMNTITUNECOA",
      "hint": {
        "index": 0,
        "letter": "d"
      }
    },
    {
      "id": 2,
      "answer": "automatically",
      "scramble": "LULTACIOYAMAT",
      "hint": {
        "index": 9,
        "letter": "a"
      }
    },
    {
      "id": 3,
      "answer": "interventions",
      "scramble": "IITNSRENNVOET",
      "hint": {
        "index": 2,
        "letter": "t"
      }
    },
    {
      "id": 4,
      "answer": "characteristics",
      "scramble": "AHCTRESCIITSACR",
      "hint": {
        "index": 1,
        "letter": "h"
      }
    },
    {
      "id": 5,
      "answer": "specifications",
      "scramble": "NPSCEAIISIOTFC",
      "hint": {
        "index": 1,
        "letter": "p"
      }
    },
    {
      "id": 6,
      "answer": "corresponding",
      "scramble": "ROEPDNROCSNGI",
      "hint": {
        "index": 7,
        "letter": "o"
      }
    },
    {
      "id": 7,
      "answer": "photographers",
      "scramble": "SETOPHRAHGPRO",
      "hint": {
        "index": 6,
        "letter": "r"
      }
    },
    {
      "id": 8,
      "answer": "parliamentary",
      "scramble": "MYERIANLTRPAA",
      "hint": {
        "index": 5,
        "letter": "a"
      }
    },
    {
      "id": 9,
      "answer": "revolutionary",
      "scramble": "EOURLYRIOTANV",
      "hint": {
        "index": 10,
        "letter": "a"
      }
    },
    {
      "id": 10,
      "answer": "identification",
      "scramble": "EIFIDTOCNATNII",
      "hint": {
        "index": 9,
        "letter": "a"
      }
    }
  ],
  "meta": {
    "generatedBy": "build_word_guess_puzzles.py",
    "seed": 1337,
    "lengthBuckets": {
      "Easy": {
        "min": 4,
        "max": 6
      },
      "Medium": {
        "min": 7,
        "max": 9
      },
      "Hard": {
        "min": 10,
        "max": 12
      },
      "Godlike": {
        "min": 13,
        "max": 25
      }
    }
  }
}