{
  "schema": "word-guess.v1",
  "dateISO": "2025-07-26",
  "level": "Godlike",
  "timerMode": "stopwatch",
  "wordsPerPuzzle": 10,
  "entries": [
    {
      "id": 1,
      "answer": "representatives",
      "scramble": "IRTSSEAEEPTEVNR",
      "hint": {
        "index": 12,
        "letter": "v"
      }
    },
    {
      "id": 2,
      "answer": "superintendent",
      "scramble": "ISNEPNTRUTEEDN",
      "hint": {
        "index": 3,
        "letter": "e"
      }
    },
    {
      "id": 3,
      "answer": "questionnaire",
      "scramble": "NRETUSANOIQIE",
      "hint": {
        "index": 12,
        "letter": "e"
      }
    },
    {
      "id": 4,
      "answer": "international",
      "scramble": "NNRANTOAITEIL",
      "hint": {
        "index": 8,
        "letter": "i"
      }
    },
    {
      "id": 5,
      "answer": "parliamentary",
      "scramble": "EIRYATMRAALPN",
      "hint": {
        "index": 6,
        "letter": "m"
      }
    },
    {
      "id": 6,
      "answer": "appropriations",
      "scramble": "NPIRAPORIPATOS",
      "hint": {
        "index": 13,
        "letter": "s"
      }
    },
    {
      "id": 7,
      "answer": "representation",
      "scramble": "EEARTISNPOTNER",
      "hint": {
        "index": 1,
        "letter": "e"
      }
    },
    {
      "id": 8,
      "answer": "starsmerchant",
      "scramble": "MHCERTNRAASST",
      "hint": {
        "index": 12,
        "letter": "t"
      }
    },
    {
      "id": 9,
      "answer": "notifications",
      "scramble": "OIATCNTFSIINO",
      "hint": {
        "index": 11,
        "letter": "n"
      }
    },
    {
      "id": 10,
      "answer": "substantially",
      "scramble": "LYTAULATIBSNS",
      "hint": {
        "index": 8,
        "letter": "i"
      }
    }
  ],
  "meta": {
    "generatedBy": "build_word_guess_puzzles.py",
    "seed": 1337,
    "lengthBuckets": {
      "Easy": {
        "min": 4,
        "max": 6
      },
      "Medium": {
        "min": 7,
        "max": 9
      },
      "Hard": {
        "min": 10,
        "max": 12
      },
      "Godlike": {
        "min": 13,
        "max": 25
      }
    }
  }
}