{
  "schema": "word-guess.v1",
  "dateISO": "2026-08-11",
  "level": "Medium",
  "timerMode": "stopwatch",
  "wordsPerPuzzle": 10,
  "entries": [
    {
      "id": 1,
      "answer": "reserves",
      "scramble": "ERSSEVER",
      "hint": {
        "index": 5,
        "letter": "v"
      }
    },
    {
      "id": 2,
      "answer": "inspired",
      "scramble": "RNDPISEI",
      "hint": {
        "index": 4,
        "letter": "i"
      }
    },
    {
      "id": 3,
      "answer": "behaviour",
      "scramble": "IVHEURAOB",
      "hint": {
        "index": 2,
        "letter": "h"
      }
    },
    {
      "id": 4,
      "answer": "hartford",
      "scramble": "RFHORATD",
      "hint": {
        "index": 7,
        "letter": "d"
      }
    },
    {
      "id": 5,
      "answer": "version",
      "scramble": "OESIRVN",
      "hint": {
        "index": 6,
        "letter": "n"
      }
    },
    {
      "id": 6,
      "answer": "perceived",
      "scramble": "CPIREVEED",
      "hint": {
        "index": 7,
        "letter": "e"
      }
    },
    {
      "id": 7,
      "answer": "secured",
      "scramble": "REESCUD",
      "hint": {
        "index": 6,
        "letter": "d"
      }
    },
    {
      "id": 8,
      "answer": "graphic",
      "scramble": "GRIPACH",
      "hint": {
        "index": 1,
        "letter": "r"
      }
    },
    {
      "id": 9,
      "answer": "expressed",
      "scramble": "XSEPSEERD",
      "hint": {
        "index": 8,
        "letter": "d"
      }
    },
    {
      "id": 10,
      "answer": "geology",
      "scramble": "OEOGGLY",
      "hint": {
        "index": 6,
        "letter": "y"
      }
    }
  ],
  "meta": {
    "generatedBy": "build_word_guess_puzzles.py",
    "seed": 1337,
    "lengthBuckets": {
      "Easy": {
        "min": 4,
        "max": 6
      },
      "Medium": {
        "min": 7,
        "max": 9
      },
      "Hard": {
        "min": 10,
        "max": 12
      },
      "Godlike": {
        "min": 13,
        "max": 25
      }
    }
  }
}