{
  "schema": "word-guess.v1",
  "dateISO": "2026-09-18",
  "level": "Challenge",
  "timerMode": "stopwatch",
  "wordsPerPuzzle": 40,
  "entries": [
    {
      "id": 1,
      "answer": "grants",
      "scramble": "TSANRG",
      "hint": {
        "index": 2,
        "letter": "a"
      },
      "sourceLevel": "Easy"
    },
    {
      "id": 2,
      "answer": "button",
      "scramble": "UNBTTO",
      "hint": {
        "index": 3,
        "letter": "t"
      },
      "sourceLevel": "Easy"
    },
    {
      "id": 3,
      "answer": "native",
      "scramble": "NAVTIE",
      "hint": {
        "index": 0,
        "letter": "n"
      },
      "sourceLevel": "Easy"
    },
    {
      "id": 4,
      "answer": "twice",
      "scramble": "TWIEC",
      "hint": {
        "index": 2,
        "letter": "i"
      },
      "sourceLevel": "Easy"
    },
    {
      "id": 5,
      "answer": "redeem",
      "scramble": "MREEED",
      "hint": {
        "index": 3,
        "letter": "e"
      },
      "sourceLevel": "Easy"
    },
    {
      "id": 6,
      "answer": "ranch",
      "scramble": "CANHR",
      "hint": {
        "index": 2,
        "letter": "n"
      },
      "sourceLevel": "Easy"
    },
    {
      "id": 7,
      "answer": "banks",
      "scramble": "KASNB",
      "hint": {
        "index": 1,
        "letter": "a"
      },
      "sourceLevel": "Easy"
    },
    {
      "id": 8,
      "answer": "boxing",
      "scramble": "XBOGNI",
      "hint": {
        "index": 4,
        "letter": "n"
      },
      "sourceLevel": "Easy"
    },
    {
      "id": 9,
      "answer": "coated",
      "scramble": "TEOCAD",
      "hint": {
        "index": 5,
        "letter": "d"
      },
      "sourceLevel": "Easy"
    },
    {
      "id": 10,
      "answer": "deals",
      "scramble": "EDALS",
      "hint": {
        "index": 2,
        "letter": "a"
      },
      "sourceLevel": "Easy"
    },
    {
      "id": 11,
      "answer": "building",
      "scramble": "DUIIGBNL",
      "hint": {
        "index": 1,
        "letter": "u"
      },
      "sourceLevel": "Medium"
    },
    {
      "id": 12,
      "answer": "started",
      "scramble": "SEARTDT",
      "hint": {
        "index": 0,
        "letter": "s"
      },
      "sourceLevel": "Medium"
    },
    {
      "id": 13,
      "answer": "premiere",
      "scramble": "REIMEPRE",
      "hint": {
        "index": 7,
        "letter": "e"
      },
      "sourceLevel": "Medium"
    },
    {
      "id": 14,
      "answer": "guestbook",
      "scramble": "GBUSEOTOK",
      "hint": {
        "index": 8,
        "letter": "k"
      },
      "sourceLevel": "Medium"
    },
    {
      "id": 15,
      "answer": "blogging",
      "scramble": "NGLGBGOI",
      "hint": {
        "index": 3,
        "letter": "g"
      },
      "sourceLevel": "Medium"
    },
    {
      "id": 16,
      "answer": "minerals",
      "scramble": "AEMRNSLI",
      "hint": {
        "index": 6,
        "letter": "l"
      },
      "sourceLevel": "Medium"
    },
    {
      "id": 17,
      "answer": "clicking",
      "scramble": "CLKNIGIC",
      "hint": {
        "index": 0,
        "letter": "c"
      },
      "sourceLevel": "Medium"
    },
    {
      "id": 18,
      "answer": "drivers",
      "scramble": "DRRSVEI",
      "hint": {
        "index": 0,
        "letter": "d"
      },
      "sourceLevel": "Medium"
    },
    {
      "id": 19,
      "answer": "printing",
      "scramble": "INNRTIGP",
      "hint": {
        "index": 4,
        "letter": "t"
      },
      "sourceLevel": "Medium"
    },
    {
      "id": 20,
      "answer": "uniform",
      "scramble": "MNUFIOR",
      "hint": {
        "index": 1,
        "letter": "n"
      },
      "sourceLevel": "Medium"
    },
    {
      "id": 21,
      "answer": "productions",
      "scramble": "DOTRUCOPINS",
      "hint": {
        "index": 4,
        "letter": "u"
      },
      "sourceLevel": "Hard"
    },
    {
      "id": 22,
      "answer": "invitations",
      "scramble": "ITSNOIVTNIA",
      "hint": {
        "index": 0,
        "letter": "i"
      },
      "sourceLevel": "Hard"
    },
    {
      "id": 23,
      "answer": "significance",
      "scramble": "NCCFISIEAGNI",
      "hint": {
        "index": 8,
        "letter": "a"
      },
      "sourceLevel": "Hard"
    },
    {
      "id": 24,
      "answer": "protecting",
      "scramble": "TROINCTEPG",
      "hint": {
        "index": 2,
        "letter": "o"
      },
      "sourceLevel": "Hard"
    },
    {
      "id": 25,
      "answer": "transaction",
      "scramble": "AATTCNNSIRO",
      "hint": {
        "index": 8,
        "letter": "i"
      },
      "sourceLevel": "Hard"
    },
    {
      "id": 26,
      "answer": "investments",
      "scramble": "NEVNIEMSSTT",
      "hint": {
        "index": 2,
        "letter": "v"
      },
      "sourceLevel": "Hard"
    },
    {
      "id": 27,
      "answer": "preservation",
      "scramble": "ETARINVRPOSE",
      "hint": {
        "index": 6,
        "letter": "v"
      },
      "sourceLevel": "Hard"
    },
    {
      "id": 28,
      "answer": "mysterious",
      "scramble": "SMSORUTIYE",
      "hint": {
        "index": 2,
        "letter": "s"
      },
      "sourceLevel": "Hard"
    },
    {
      "id": 29,
      "answer": "punishment",
      "scramble": "NESTUPHINM",
      "hint": {
        "index": 8,
        "letter": "n"
      },
      "sourceLevel": "Hard"
    },
    {
      "id": 30,
      "answer": "developments",
      "scramble": "TNVEEDSMLPEO",
      "hint": {
        "index": 7,
        "letter": "m"
      },
      "sourceLevel": "Hard"
    },
    {
      "id": 31,
      "answer": "representation",
      "scramble": "TRSTEAIPNOEREN",
      "hint": {
        "index": 13,
        "letter": "n"
      },
      "sourceLevel": "Godlike"
    },
    {
      "id": 32,
      "answer": "pharmaceutical",
      "scramble": "MLARACAPCUTHEI",
      "hint": {
        "index": 3,
        "letter": "r"
      },
      "sourceLevel": "Godlike"
    },
    {
      "id": 33,
      "answer": "extraordinary",
      "scramble": "RTARANYDIOXRE",
      "hint": {
        "index": 8,
        "letter": "i"
      },
      "sourceLevel": "Godlike"
    },
    {
      "id": 34,
      "answer": "investigators",
      "scramble": "TSISOVITAGREN",
      "hint": {
        "index": 8,
        "letter": "a"
      },
      "sourceLevel": "Godlike"
    },
    {
      "id": 35,
      "answer": "championships",
      "scramble": "CSPOISNPHAHMI",
      "hint": {
        "index": 0,
        "letter": "c"
      },
      "sourceLevel": "Godlike"
    },
    {
      "id": 36,
      "answer": "telecommunications",
      "scramble": "SOECLICMEMTUOTNNAI",
      "hint": {
        "index": 13,
        "letter": "t"
      },
      "sourceLevel": "Godlike"
    },
    {
      "id": 37,
      "answer": "installations",
      "scramble": "LAINNTOTSLAIS",
      "hint": {
        "index": 12,
        "letter": "s"
      },
      "sourceLevel": "Godlike"
    },
    {
      "id": 38,
      "answer": "documentation",
      "scramble": "ODTUCNOTIMEAN",
      "hint": {
        "index": 3,
        "letter": "u"
      },
      "sourceLevel": "Godlike"
    },
    {
      "id": 39,
      "answer": "accreditation",
      "scramble": "ICTOARDACTNEI",
      "hint": {
        "index": 1,
        "letter": "c"
      },
      "sourceLevel": "Godlike"
    },
    {
      "id": 40,
      "answer": "comprehensive",
      "scramble": "IHMECVONSERPE",
      "hint": {
        "index": 2,
        "letter": "m"
      },
      "sourceLevel": "Godlike"
    }
  ],
  "meta": {
    "generatedBy": "build_word_guess_puzzles.py",
    "seed": 1337,
    "challengeSeedOffset": 99991,
    "lengthBuckets": {
      "Easy": {
        "min": 4,
        "max": 6
      },
      "Medium": {
        "min": 7,
        "max": 9
      },
      "Hard": {
        "min": 10,
        "max": 12
      },
      "Godlike": {
        "min": 13,
        "max": 25
      }
    }
  }
}