{
  "schema": "word-guess.v1",
  "dateISO": "2026-06-15",
  "level": "Godlike",
  "timerMode": "stopwatch",
  "wordsPerPuzzle": 10,
  "entries": [
    {
      "id": 1,
      "answer": "discrimination",
      "scramble": "NCDRMIITIOIASN",
      "hint": {
        "index": 5,
        "letter": "i"
      }
    },
    {
      "id": 2,
      "answer": "collaborative",
      "scramble": "OEOLBVTRCLAAI",
      "hint": {
        "index": 7,
        "letter": "r"
      }
    },
    {
      "id": 3,
      "answer": "configurations",
      "scramble": "SOTONUIGANICFR",
      "hint": {
        "index": 1,
        "letter": "o"
      }
    },
    {
      "id": 4,
      "answer": "opportunities",
      "scramble": "UPPORNTTIOIES",
      "hint": {
        "index": 1,
        "letter": "p"
      }
    },
    {
      "id": 5,
      "answer": "environmental",
      "scramble": "OEVMTIEARNLNN",
      "hint": {
        "index": 9,
        "letter": "n"
      }
    },
    {
      "id": 6,
      "answer": "qualifications",
      "scramble": "UFOIIACILSTQAN",
      "hint": {
        "index": 4,
        "letter": "i"
      }
    },
    {
      "id": 7,
      "answer": "communication",
      "scramble": "UMCNTNIOCOIAM",
      "hint": {
        "index": 6,
        "letter": "i"
      }
    },
    {
      "id": 8,
      "answer": "functionality",
      "scramble": "ONICYLTIAUFTN",
      "hint": {
        "index": 8,
        "letter": "a"
      }
    },
    {
      "id": 9,
      "answer": "characterized",
      "scramble": "CEATZEDARCIHR",
      "hint": {
        "index": 0,
        "letter": "c"
      }
    },
    {
      "id": 10,
      "answer": "considerations",
      "scramble": "SANRICOEODISNT",
      "hint": {
        "index": 2,
        "letter": "n"
      }
    }
  ],
  "meta": {
    "generatedBy": "build_word_guess_puzzles.py",
    "seed": 1337,
    "lengthBuckets": {
      "Easy": {
        "min": 4,
        "max": 6
      },
      "Medium": {
        "min": 7,
        "max": 9
      },
      "Hard": {
        "min": 10,
        "max": 12
      },
      "Godlike": {
        "min": 13,
        "max": 25
      }
    }
  }
}