{
  "schema": "word-guess.v1",
  "dateISO": "2026-04-05",
  "level": "Easy",
  "timerMode": "stopwatch",
  "wordsPerPuzzle": 10,
  "entries": [
    {
      "id": 1,
      "answer": "sans",
      "scramble": "SSNA",
      "hint": {
        "index": 2,
        "letter": "n"
      }
    },
    {
      "id": 2,
      "answer": "chile",
      "scramble": "CIHLE",
      "hint": {
        "index": 3,
        "letter": "l"
      }
    },
    {
      "id": 3,
      "answer": "leader",
      "scramble": "EERLDA",
      "hint": {
        "index": 1,
        "letter": "e"
      }
    },
    {
      "id": 4,
      "answer": "four",
      "scramble": "FUOR",
      "hint": {
        "index": 0,
        "letter": "f"
      }
    },
    {
      "id": 5,
      "answer": "badly",
      "scramble": "DAYBL",
      "hint": {
        "index": 1,
        "letter": "a"
      }
    },
    {
      "id": 6,
      "answer": "drum",
      "scramble": "URMD",
      "hint": {
        "index": 1,
        "letter": "r"
      }
    },
    {
      "id": 7,
      "answer": "hull",
      "scramble": "HLUL",
      "hint": {
        "index": 0,
        "letter": "h"
      }
    },
    {
      "id": 8,
      "answer": "plugin",
      "scramble": "PIUGLN",
      "hint": {
        "index": 2,
        "letter": "u"
      }
    },
    {
      "id": 9,
      "answer": "seen",
      "scramble": "NSEE",
      "hint": {
        "index": 2,
        "letter": "e"
      }
    },
    {
      "id": 10,
      "answer": "tape",
      "scramble": "ATPE",
      "hint": {
        "index": 2,
        "letter": "p"
      }
    }
  ],
  "meta": {
    "generatedBy": "build_word_guess_puzzles.py",
    "seed": 1337,
    "lengthBuckets": {
      "Easy": {
        "min": 4,
        "max": 6
      },
      "Medium": {
        "min": 7,
        "max": 9
      },
      "Hard": {
        "min": 10,
        "max": 12
      },
      "Godlike": {
        "min": 13,
        "max": 25
      }
    }
  }
}