{
  "schema": "word-guess.v1",
  "dateISO": "2025-03-31",
  "level": "Challenge",
  "timerMode": "stopwatch",
  "wordsPerPuzzle": 40,
  "entries": [
    {
      "id": 1,
      "answer": "warned",
      "scramble": "WEANRD",
      "hint": {
        "index": 0,
        "letter": "w"
      },
      "sourceLevel": "Easy"
    },
    {
      "id": 2,
      "answer": "cooked",
      "scramble": "DCOKEO",
      "hint": {
        "index": 4,
        "letter": "e"
      },
      "sourceLevel": "Easy"
    },
    {
      "id": 3,
      "answer": "seal",
      "scramble": "SALE",
      "hint": {
        "index": 0,
        "letter": "s"
      },
      "sourceLevel": "Easy"
    },
    {
      "id": 4,
      "answer": "sorts",
      "scramble": "ORSTS",
      "hint": {
        "index": 3,
        "letter": "t"
      },
      "sourceLevel": "Easy"
    },
    {
      "id": 5,
      "answer": "beings",
      "scramble": "BSNGEI",
      "hint": {
        "index": 0,
        "letter": "b"
      },
      "sourceLevel": "Easy"
    },
    {
      "id": 6,
      "answer": "game",
      "scramble": "EAMG",
      "hint": {
        "index": 1,
        "letter": "a"
      },
      "sourceLevel": "Easy"
    },
    {
      "id": 7,
      "answer": "panama",
      "scramble": "PANMAA",
      "hint": {
        "index": 2,
        "letter": "n"
      },
      "sourceLevel": "Easy"
    },
    {
      "id": 8,
      "answer": "cells",
      "scramble": "CSELL",
      "hint": {
        "index": 0,
        "letter": "c"
      },
      "sourceLevel": "Easy"
    },
    {
      "id": 9,
      "answer": "colin",
      "scramble": "CNOIL",
      "hint": {
        "index": 0,
        "letter": "c"
      },
      "sourceLevel": "Easy"
    },
    {
      "id": 10,
      "answer": "enzyme",
      "scramble": "YNZEEM",
      "hint": {
        "index": 1,
        "letter": "n"
      },
      "sourceLevel": "Easy"
    },
    {
      "id": 11,
      "answer": "vintage",
      "scramble": "GTINAVE",
      "hint": {
        "index": 4,
        "letter": "a"
      },
      "sourceLevel": "Medium"
    },
    {
      "id": 12,
      "answer": "disagree",
      "scramble": "EDIASERG",
      "hint": {
        "index": 3,
        "letter": "a"
      },
      "sourceLevel": "Medium"
    },
    {
      "id": 13,
      "answer": "motivated",
      "scramble": "ATTIEMVOD",
      "hint": {
        "index": 3,
        "letter": "i"
      },
      "sourceLevel": "Medium"
    },
    {
      "id": 14,
      "answer": "handhelds",
      "scramble": "SHEDHLNAD",
      "hint": {
        "index": 3,
        "letter": "d"
      },
      "sourceLevel": "Medium"
    },
    {
      "id": 15,
      "answer": "forecasts",
      "scramble": "FCRETSOAS",
      "hint": {
        "index": 8,
        "letter": "s"
      },
      "sourceLevel": "Medium"
    },
    {
      "id": 16,
      "answer": "managing",
      "scramble": "AANNIMGG",
      "hint": {
        "index": 7,
        "letter": "g"
      },
      "sourceLevel": "Medium"
    },
    {
      "id": 17,
      "answer": "constant",
      "scramble": "ATOSTNNC",
      "hint": {
        "index": 4,
        "letter": "t"
      },
      "sourceLevel": "Medium"
    },
    {
      "id": 18,
      "answer": "evening",
      "scramble": "VENGIEN",
      "hint": {
        "index": 4,
        "letter": "i"
      },
      "sourceLevel": "Medium"
    },
    {
      "id": 19,
      "answer": "journals",
      "scramble": "JLURNOSA",
      "hint": {
        "index": 4,
        "letter": "n"
      },
      "sourceLevel": "Medium"
    },
    {
      "id": 20,
      "answer": "situation",
      "scramble": "SITAOINTU",
      "hint": {
        "index": 0,
        "letter": "s"
      },
      "sourceLevel": "Medium"
    },
    {
      "id": 21,
      "answer": "collecting",
      "scramble": "GONLTECICL",
      "hint": {
        "index": 3,
        "letter": "l"
      },
      "sourceLevel": "Hard"
    },
    {
      "id": 22,
      "answer": "ejaculation",
      "scramble": "IJALACUOTEN",
      "hint": {
        "index": 10,
        "letter": "n"
      },
      "sourceLevel": "Hard"
    },
    {
      "id": 23,
      "answer": "regression",
      "scramble": "GEISERSRON",
      "hint": {
        "index": 9,
        "letter": "n"
      },
      "sourceLevel": "Hard"
    },
    {
      "id": 24,
      "answer": "originally",
      "scramble": "ORILAGNILY",
      "hint": {
        "index": 9,
        "letter": "y"
      },
      "sourceLevel": "Hard"
    },
    {
      "id": 25,
      "answer": "substitute",
      "scramble": "SBEITSTUUT",
      "hint": {
        "index": 4,
        "letter": "t"
      },
      "sourceLevel": "Hard"
    },
    {
      "id": 26,
      "answer": "mathematical",
      "scramble": "IATMCTLAAMEH",
      "hint": {
        "index": 2,
        "letter": "t"
      },
      "sourceLevel": "Hard"
    },
    {
      "id": 27,
      "answer": "nationally",
      "scramble": "AONINLYLTA",
      "hint": {
        "index": 3,
        "letter": "i"
      },
      "sourceLevel": "Hard"
    },
    {
      "id": 28,
      "answer": "respiratory",
      "scramble": "IYOERTARPSR",
      "hint": {
        "index": 6,
        "letter": "a"
      },
      "sourceLevel": "Hard"
    },
    {
      "id": 29,
      "answer": "configured",
      "scramble": "RNFGIODCEU",
      "hint": {
        "index": 8,
        "letter": "e"
      },
      "sourceLevel": "Hard"
    },
    {
      "id": 30,
      "answer": "alphabetical",
      "scramble": "HLCPAIABTALE",
      "hint": {
        "index": 4,
        "letter": "a"
      },
      "sourceLevel": "Hard"
    },
    {
      "id": 31,
      "answer": "internationally",
      "scramble": "LEONIRNTTNIALAY",
      "hint": {
        "index": 14,
        "letter": "y"
      },
      "sourceLevel": "Godlike"
    },
    {
      "id": 32,
      "answer": "concentration",
      "scramble": "TORCEIANNONCT",
      "hint": {
        "index": 4,
        "letter": "e"
      },
      "sourceLevel": "Godlike"
    },
    {
      "id": 33,
      "answer": "liechtenstein",
      "scramble": "HNINTEETIECLS",
      "hint": {
        "index": 6,
        "letter": "e"
      },
      "sourceLevel": "Godlike"
    },
    {
      "id": 34,
      "answer": "rehabilitation",
      "scramble": "TARIBOITNAHILE",
      "hint": {
        "index": 9,
        "letter": "a"
      },
      "sourceLevel": "Godlike"
    },
    {
      "id": 35,
      "answer": "architectural",
      "scramble": "ACRRITHLEUTAC",
      "hint": {
        "index": 4,
        "letter": "i"
      },
      "sourceLevel": "Godlike"
    },
    {
      "id": 36,
      "answer": "communications",
      "scramble": "UINOSMOCAIMNCT",
      "hint": {
        "index": 7,
        "letter": "c"
      },
      "sourceLevel": "Godlike"
    },
    {
      "id": 37,
      "answer": "administrative",
      "scramble": "ITRTNIDAESAIVM",
      "hint": {
        "index": 12,
        "letter": "v"
      },
      "sourceLevel": "Godlike"
    },
    {
      "id": 38,
      "answer": "organizational",
      "scramble": "NILTGAAAIORNOZ",
      "hint": {
        "index": 7,
        "letter": "a"
      },
      "sourceLevel": "Godlike"
    },
    {
      "id": 39,
      "answer": "specifications",
      "scramble": "EPIISAONSCICFT",
      "hint": {
        "index": 1,
        "letter": "p"
      },
      "sourceLevel": "Godlike"
    },
    {
      "id": 40,
      "answer": "representatives",
      "scramble": "EVAPSSENTEETRRI",
      "hint": {
        "index": 7,
        "letter": "n"
      },
      "sourceLevel": "Godlike"
    }
  ],
  "meta": {
    "generatedBy": "build_word_guess_puzzles.py",
    "seed": 1337,
    "challengeSeedOffset": 99991,
    "lengthBuckets": {
      "Easy": {
        "min": 4,
        "max": 6
      },
      "Medium": {
        "min": 7,
        "max": 9
      },
      "Hard": {
        "min": 10,
        "max": 12
      },
      "Godlike": {
        "min": 13,
        "max": 25
      }
    }
  }
}