{
  "schema": "word-guess.v1",
  "dateISO": "2025-08-30",
  "level": "Medium",
  "timerMode": "stopwatch",
  "wordsPerPuzzle": 10,
  "entries": [
    {
      "id": 1,
      "answer": "decided",
      "scramble": "EEDCDDI",
      "hint": {
        "index": 1,
        "letter": "e"
      }
    },
    {
      "id": 2,
      "answer": "filters",
      "scramble": "SIETLFR",
      "hint": {
        "index": 1,
        "letter": "i"
      }
    },
    {
      "id": 3,
      "answer": "physics",
      "scramble": "ISSPYCH",
      "hint": {
        "index": 5,
        "letter": "c"
      }
    },
    {
      "id": 4,
      "answer": "authority",
      "scramble": "AYITOURHT",
      "hint": {
        "index": 4,
        "letter": "o"
      }
    },
    {
      "id": 5,
      "answer": "branches",
      "scramble": "RCSANHEB",
      "hint": {
        "index": 6,
        "letter": "e"
      }
    },
    {
      "id": 6,
      "answer": "restrict",
      "scramble": "TRTSRIEC",
      "hint": {
        "index": 4,
        "letter": "r"
      }
    },
    {
      "id": 7,
      "answer": "cameras",
      "scramble": "CAARSME",
      "hint": {
        "index": 1,
        "letter": "a"
      }
    },
    {
      "id": 8,
      "answer": "riverside",
      "scramble": "REIVIRSED",
      "hint": {
        "index": 0,
        "letter": "r"
      }
    },
    {
      "id": 9,
      "answer": "dealers",
      "scramble": "ASRLEDE",
      "hint": {
        "index": 3,
        "letter": "l"
      }
    },
    {
      "id": 10,
      "answer": "specially",
      "scramble": "SAPYECLLI",
      "hint": {
        "index": 6,
        "letter": "l"
      }
    }
  ],
  "meta": {
    "generatedBy": "build_word_guess_puzzles.py",
    "seed": 1337,
    "lengthBuckets": {
      "Easy": {
        "min": 4,
        "max": 6
      },
      "Medium": {
        "min": 7,
        "max": 9
      },
      "Hard": {
        "min": 10,
        "max": 12
      },
      "Godlike": {
        "min": 13,
        "max": 25
      }
    }
  }
}