{
  "schema": "word-guess.v1",
  "dateISO": "2025-04-02",
  "level": "Easy",
  "timerMode": "stopwatch",
  "wordsPerPuzzle": 10,
  "entries": [
    {
      "id": 1,
      "answer": "when",
      "scramble": "EWHN",
      "hint": {
        "index": 3,
        "letter": "n"
      }
    },
    {
      "id": 2,
      "answer": "drama",
      "scramble": "RAAMD",
      "hint": {
        "index": 3,
        "letter": "m"
      }
    },
    {
      "id": 3,
      "answer": "charm",
      "scramble": "CHMRA",
      "hint": {
        "index": 1,
        "letter": "h"
      }
    },
    {
      "id": 4,
      "answer": "circus",
      "scramble": "IUCRCS",
      "hint": {
        "index": 5,
        "letter": "s"
      }
    },
    {
      "id": 5,
      "answer": "pubmed",
      "scramble": "PEBMDU",
      "hint": {
        "index": 0,
        "letter": "p"
      }
    },
    {
      "id": 6,
      "answer": "secure",
      "scramble": "UEECRS",
      "hint": {
        "index": 4,
        "letter": "r"
      }
    },
    {
      "id": 7,
      "answer": "smtp",
      "scramble": "PMTS",
      "hint": {
        "index": 1,
        "letter": "m"
      }
    },
    {
      "id": 8,
      "answer": "deemed",
      "scramble": "EEEDMD",
      "hint": {
        "index": 5,
        "letter": "d"
      }
    },
    {
      "id": 9,
      "answer": "wicked",
      "scramble": "DICKWE",
      "hint": {
        "index": 2,
        "letter": "c"
      }
    },
    {
      "id": 10,
      "answer": "info",
      "scramble": "NIFO",
      "hint": {
        "index": 2,
        "letter": "f"
      }
    }
  ],
  "meta": {
    "generatedBy": "build_word_guess_puzzles.py",
    "seed": 1337,
    "lengthBuckets": {
      "Easy": {
        "min": 4,
        "max": 6
      },
      "Medium": {
        "min": 7,
        "max": 9
      },
      "Hard": {
        "min": 10,
        "max": 12
      },
      "Godlike": {
        "min": 13,
        "max": 25
      }
    }
  }
}