{
  "schema": "word-guess.v1",
  "dateISO": "2025-09-25",
  "level": "Easy",
  "timerMode": "stopwatch",
  "wordsPerPuzzle": 10,
  "entries": [
    {
      "id": 1,
      "answer": "ticket",
      "scramble": "KICTET",
      "hint": {
        "index": 4,
        "letter": "e"
      }
    },
    {
      "id": 2,
      "answer": "theme",
      "scramble": "TMEHE",
      "hint": {
        "index": 4,
        "letter": "e"
      }
    },
    {
      "id": 3,
      "answer": "exceed",
      "scramble": "XECDEE",
      "hint": {
        "index": 2,
        "letter": "c"
      }
    },
    {
      "id": 4,
      "answer": "serve",
      "scramble": "RSEVE",
      "hint": {
        "index": 4,
        "letter": "e"
      }
    },
    {
      "id": 5,
      "answer": "jaguar",
      "scramble": "AGJURA",
      "hint": {
        "index": 3,
        "letter": "u"
      }
    },
    {
      "id": 6,
      "answer": "likes",
      "scramble": "LIKSE",
      "hint": {
        "index": 2,
        "letter": "k"
      }
    },
    {
      "id": 7,
      "answer": "delta",
      "scramble": "LDETA",
      "hint": {
        "index": 3,
        "letter": "t"
      }
    },
    {
      "id": 8,
      "answer": "buck",
      "scramble": "BUKC",
      "hint": {
        "index": 0,
        "letter": "b"
      }
    },
    {
      "id": 9,
      "answer": "jump",
      "scramble": "UMJP",
      "hint": {
        "index": 3,
        "letter": "p"
      }
    },
    {
      "id": 10,
      "answer": "speeds",
      "scramble": "EPESSD",
      "hint": {
        "index": 2,
        "letter": "e"
      }
    }
  ],
  "meta": {
    "generatedBy": "build_word_guess_puzzles.py",
    "seed": 1337,
    "lengthBuckets": {
      "Easy": {
        "min": 4,
        "max": 6
      },
      "Medium": {
        "min": 7,
        "max": 9
      },
      "Hard": {
        "min": 10,
        "max": 12
      },
      "Godlike": {
        "min": 13,
        "max": 25
      }
    }
  }
}