{
  "schema": "word-guess.v1",
  "dateISO": "2025-02-17",
  "level": "Challenge",
  "timerMode": "stopwatch",
  "wordsPerPuzzle": 40,
  "entries": [
    {
      "id": 1,
      "answer": "poet",
      "scramble": "TOEP",
      "hint": {
        "index": 1,
        "letter": "o"
      },
      "sourceLevel": "Easy"
    },
    {
      "id": 2,
      "answer": "abuse",
      "scramble": "AUBES",
      "hint": {
        "index": 0,
        "letter": "a"
      },
      "sourceLevel": "Easy"
    },
    {
      "id": 3,
      "answer": "minds",
      "scramble": "MNIDS",
      "hint": {
        "index": 0,
        "letter": "m"
      },
      "sourceLevel": "Easy"
    },
    {
      "id": 4,
      "answer": "motels",
      "scramble": "MTOSLE",
      "hint": {
        "index": 0,
        "letter": "m"
      },
      "sourceLevel": "Easy"
    },
    {
      "id": 5,
      "answer": "visual",
      "scramble": "ASIUVL",
      "hint": {
        "index": 3,
        "letter": "u"
      },
      "sourceLevel": "Easy"
    },
    {
      "id": 6,
      "answer": "except",
      "scramble": "EETPXC",
      "hint": {
        "index": 0,
        "letter": "e"
      },
      "sourceLevel": "Easy"
    },
    {
      "id": 7,
      "answer": "couple",
      "scramble": "CLUPOE",
      "hint": {
        "index": 5,
        "letter": "e"
      },
      "sourceLevel": "Easy"
    },
    {
      "id": 8,
      "answer": "clips",
      "scramble": "CIPSL",
      "hint": {
        "index": 0,
        "letter": "c"
      },
      "sourceLevel": "Easy"
    },
    {
      "id": 9,
      "answer": "entity",
      "scramble": "TNEITY",
      "hint": {
        "index": 1,
        "letter": "n"
      },
      "sourceLevel": "Easy"
    },
    {
      "id": 10,
      "answer": "main",
      "scramble": "MANI",
      "hint": {
        "index": 0,
        "letter": "m"
      },
      "sourceLevel": "Easy"
    },
    {
      "id": 11,
      "answer": "worldsex",
      "scramble": "DOSXWERL",
      "hint": {
        "index": 1,
        "letter": "o"
      },
      "sourceLevel": "Medium"
    },
    {
      "id": 12,
      "answer": "similarly",
      "scramble": "RYLMIISLA",
      "hint": {
        "index": 7,
        "letter": "l"
      },
      "sourceLevel": "Medium"
    },
    {
      "id": 13,
      "answer": "temporary",
      "scramble": "OMAETRPRY",
      "hint": {
        "index": 7,
        "letter": "r"
      },
      "sourceLevel": "Medium"
    },
    {
      "id": 14,
      "answer": "reuters",
      "scramble": "TEUERRS",
      "hint": {
        "index": 6,
        "letter": "s"
      },
      "sourceLevel": "Medium"
    },
    {
      "id": 15,
      "answer": "conscious",
      "scramble": "OCUOSICNS",
      "hint": {
        "index": 8,
        "letter": "s"
      },
      "sourceLevel": "Medium"
    },
    {
      "id": 16,
      "answer": "instead",
      "scramble": "TENDSAI",
      "hint": {
        "index": 5,
        "letter": "a"
      },
      "sourceLevel": "Medium"
    },
    {
      "id": 17,
      "answer": "registrar",
      "scramble": "TRREGSIAR",
      "hint": {
        "index": 7,
        "letter": "a"
      },
      "sourceLevel": "Medium"
    },
    {
      "id": 18,
      "answer": "portland",
      "scramble": "LNRPOTAD",
      "hint": {
        "index": 7,
        "letter": "d"
      },
      "sourceLevel": "Medium"
    },
    {
      "id": 19,
      "answer": "strictly",
      "scramble": "RTCYLTSI",
      "hint": {
        "index": 5,
        "letter": "t"
      },
      "sourceLevel": "Medium"
    },
    {
      "id": 20,
      "answer": "electron",
      "scramble": "TNOLERCE",
      "hint": {
        "index": 5,
        "letter": "r"
      },
      "sourceLevel": "Medium"
    },
    {
      "id": 21,
      "answer": "influences",
      "scramble": "IESCNUEFNL",
      "hint": {
        "index": 0,
        "letter": "i"
      },
      "sourceLevel": "Hard"
    },
    {
      "id": 22,
      "answer": "continuing",
      "scramble": "NOCUIGNINT",
      "hint": {
        "index": 4,
        "letter": "i"
      },
      "sourceLevel": "Hard"
    },
    {
      "id": 23,
      "answer": "deutschland",
      "scramble": "DEUHTLACNDS",
      "hint": {
        "index": 0,
        "letter": "d"
      },
      "sourceLevel": "Hard"
    },
    {
      "id": 24,
      "answer": "simplified",
      "scramble": "IFMIISELPD",
      "hint": {
        "index": 9,
        "letter": "d"
      },
      "sourceLevel": "Hard"
    },
    {
      "id": 25,
      "answer": "assignment",
      "scramble": "SNTEGIMNSA",
      "hint": {
        "index": 4,
        "letter": "g"
      },
      "sourceLevel": "Hard"
    },
    {
      "id": 26,
      "answer": "preventing",
      "scramble": "GRENITEVNP",
      "hint": {
        "index": 8,
        "letter": "n"
      },
      "sourceLevel": "Hard"
    },
    {
      "id": 27,
      "answer": "governments",
      "scramble": "TVMERESNOGN",
      "hint": {
        "index": 3,
        "letter": "e"
      },
      "sourceLevel": "Hard"
    },
    {
      "id": 28,
      "answer": "explanation",
      "scramble": "TEPNIAAOXNL",
      "hint": {
        "index": 6,
        "letter": "a"
      },
      "sourceLevel": "Hard"
    },
    {
      "id": 29,
      "answer": "determined",
      "scramble": "TRMIDEEEND",
      "hint": {
        "index": 9,
        "letter": "d"
      },
      "sourceLevel": "Hard"
    },
    {
      "id": 30,
      "answer": "nomination",
      "scramble": "ONNOTNIIAM",
      "hint": {
        "index": 7,
        "letter": "i"
      },
      "sourceLevel": "Hard"
    },
    {
      "id": 31,
      "answer": "administrators",
      "scramble": "AMOSRNATSDIIRT",
      "hint": {
        "index": 12,
        "letter": "r"
      },
      "sourceLevel": "Godlike"
    },
    {
      "id": 32,
      "answer": "miscellaneous",
      "scramble": "ULCNEEALIOMSS",
      "hint": {
        "index": 12,
        "letter": "s"
      },
      "sourceLevel": "Godlike"
    },
    {
      "id": 33,
      "answer": "contributions",
      "scramble": "ITNUSTCOBNIOR",
      "hint": {
        "index": 2,
        "letter": "n"
      },
      "sourceLevel": "Godlike"
    },
    {
      "id": 34,
      "answer": "representations",
      "scramble": "EEAOSTERNNRSTPI",
      "hint": {
        "index": 1,
        "letter": "e"
      },
      "sourceLevel": "Godlike"
    },
    {
      "id": 35,
      "answer": "corresponding",
      "scramble": "GCPRDSROOENIN",
      "hint": {
        "index": 3,
        "letter": "r"
      },
      "sourceLevel": "Godlike"
    },
    {
      "id": 36,
      "answer": "complications",
      "scramble": "CONOPALCMIIST",
      "hint": {
        "index": 1,
        "letter": "o"
      },
      "sourceLevel": "Godlike"
    },
    {
      "id": 37,
      "answer": "identification",
      "scramble": "FONDIAINCTIITE",
      "hint": {
        "index": 8,
        "letter": "c"
      },
      "sourceLevel": "Godlike"
    },
    {
      "id": 38,
      "answer": "mediterranean",
      "scramble": "RINETAERDEMAN",
      "hint": {
        "index": 12,
        "letter": "n"
      },
      "sourceLevel": "Godlike"
    },
    {
      "id": 39,
      "answer": "substantially",
      "scramble": "SSTTINAAYUBLL",
      "hint": {
        "index": 11,
        "letter": "l"
      },
      "sourceLevel": "Godlike"
    },
    {
      "id": 40,
      "answer": "psychological",
      "scramble": "CPLCSGOYOLAHI",
      "hint": {
        "index": 3,
        "letter": "c"
      },
      "sourceLevel": "Godlike"
    }
  ],
  "meta": {
    "generatedBy": "build_word_guess_puzzles.py",
    "seed": 1337,
    "challengeSeedOffset": 99991,
    "lengthBuckets": {
      "Easy": {
        "min": 4,
        "max": 6
      },
      "Medium": {
        "min": 7,
        "max": 9
      },
      "Hard": {
        "min": 10,
        "max": 12
      },
      "Godlike": {
        "min": 13,
        "max": 25
      }
    }
  }
}